llama_index/py.typed
llama_index/vector_stores/solr/__init__.py
llama_index/vector_stores/solr/base.py
llama_index/vector_stores/solr/constants.py
llama_index/vector_stores/solr/query_utils.py
llama_index/vector_stores/solr/types.py
llama_index/vector_stores/solr/client/__init__.py
llama_index/vector_stores/solr/client/_base.py
llama_index/vector_stores/solr/client/async_.py
llama_index/vector_stores/solr/client/responses.py
llama_index/vector_stores/solr/client/sync.py
llama_index/vector_stores/solr/client/utils.py
llama_index_vector_stores_solr-0.1.0.dist-info/METADATA
llama_index_vector_stores_solr-0.1.0.dist-info/WHEEL
llama_index_vector_stores_solr-0.1.0.dist-info/licenses/LICENSE
llama_index_vector_stores_solr-0.1.0.dist-info/RECORD
