Metadata-Version: 2.4
Name: llama-index-vector-stores-solr
Version: 0.1.0
Summary: llama-index vector_stores Apache Solr integration
Author-email: Atharva Tendle <atendle@bloomberg.net>, Leon Zhou <lzhou286@bloomberg.net>, Steven Butler <sbutler81@bloomberg.net>, Vikramjeet Das <vdas22@bloomberg.net>, Xiaoyu Ouyang <xouyang1@bloomberg.net>, Yong Zhuang <yzhuang52@bloomberg.net>
License-Expression: MIT
License-File: LICENSE
Requires-Python: <4.0,>=3.9
Requires-Dist: aiosolr<5; python_version < '3.10'
Requires-Dist: aiosolr>=5.0.0; python_version >= '3.10'
Requires-Dist: llama-index-core<0.15,>=0.14.0
Requires-Dist: numpy>=2.0.2
Requires-Dist: pydantic>=2.11.7
Requires-Dist: pysolr>=3.10.0
Requires-Dist: typing-extensions>=4.15.0
